marimo_pydantic_form/__init__.py
marimo_pydantic_form/_form.py
marimo_pydantic_form/_pydantic_helper.py
marimo_pydantic_form-0.1.1.dist-info/WHEEL
marimo_pydantic_form-0.1.1.dist-info/METADATA
marimo_pydantic_form-0.1.1.dist-info/RECORD
