Metadata-Version: 2.3
Name: marimo-pydantic-form
Version: 0.1.1
Summary: marimo form defined by a Pydantic model
Author: Shunichiro Nomura
Author-email: Shunichiro Nomura <nomura@space.t.u-tokyo.ac.jp>
Requires-Dist: marimo>=0.18.4
Requires-Dist: pydantic>=2.12.5
Requires-Python: >=3.13
